{
  "firstLayout": "",
  "gdVersion": {
    "build": 99,
    "major": 4,
    "minor": 0,
    "revision": 0
  },
  "properties": {
    "adaptGameResolutionAtRuntime": true,
    "folderProject": false,
    "orientation": "landscape",
    "packageName": "com.example.gamename",
    "projectUuid": "5b451d7b-0d57-4e23-a7ba-3e2e4a0df021",
    "scaleMode": "linear",
    "sizeOnStartupMode": "adaptWidth",
    "useExternalSourceFiles": false,
    "version": "1.0.0",
    "name": "Project",
    "author": "",
    "windowWidth": 800,
    "windowHeight": 600,
    "latestCompilationDirectory": "",
    "maxFPS": 60,
    "minFPS": 20,
    "verticalSync": false,
    "platformSpecificAssets": {},
    "loadingScreen": {
      "showGDevelopSplash": false
    },
    "extensionProperties": [],
    "extensions": [
      {
        "name": "BuiltinObject"
      },
      {
        "name": "BuiltinAudio"
      },
      {
        "name": "BuiltinVariables"
      },
      {
        "name": "BuiltinTime"
      },
      {
        "name": "BuiltinMouse"
      },
      {
        "name": "BuiltinKeyboard"
      },
      {
        "name": "BuiltinJoystick"
      },
      {
        "name": "BuiltinCamera"
      },
      {
        "name": "BuiltinWindow"
      },
      {
        "name": "BuiltinFile"
      },
      {
        "name": "BuiltinNetwork"
      },
      {
        "name": "BuiltinScene"
      },
      {
        "name": "BuiltinAdvanced"
      },
      {
        "name": "Sprite"
      },
      {
        "name": "BuiltinCommonInstructions"
      },
      {
        "name": "BuiltinCommonConversions"
      },
      {
        "name": "BuiltinStringInstructions"
      },
      {
        "name": "BuiltinMathematicalTools"
      },
      {
        "name": "BuiltinExternalLayouts"
      }
    ],
    "platforms": [
      {
        "name": "GDevelop JS platform"
      }
    ],
    "currentPlatform": "GDevelop JS platform"
  },
  "resources": {
    "resources": [
      {
        "alwaysLoaded": false,
        "file": "assets/Green Disc.png",
        "kind": "image",
        "metadata": "",
        "name": "Green Disc.png",
        "smoothed": true,
        "userAdded": false,
        "origin": {
          "identifier": "https://resources.gdevelop-app.com/assets/Abstract Platformer Pack (370 assets)/PNG/Items/Green Disc.png",
          "name": "gdevelop-asset-store"
        }
      },
      {
        "alwaysLoaded": false,
        "file": "assets/Red Disc.png",
        "kind": "image",
        "metadata": "",
        "name": "Red Disc.png",
        "smoothed": true,
        "userAdded": false,
        "origin": {
          "identifier": "https://resources.gdevelop-app.com/assets/Abstract Platformer Pack (370 assets)/PNG/Items/Red Disc.png",
          "name": "gdevelop-asset-store"
        }
      },
      {
        "alwaysLoaded": false,
        "file": "assets/Green Disc.png",
        "kind": "image",
        "metadata": "",
        "name": "assets\\Green Disc.png",
        "smoothed": true,
        "userAdded": false
      },
      {
        "alwaysLoaded": false,
        "file": "halfling bardo.jpg",
        "kind": "image",
        "metadata": "",
        "name": "halfling bardo.jpg",
        "smoothed": true,
        "userAdded": true
      },
      {
        "alwaysLoaded": false,
        "file": "teste.png",
        "kind": "image",
        "metadata": "",
        "name": "teste.png",
        "smoothed": true,
        "userAdded": true
      },
      {
        "alwaysLoaded": false,
        "file": "tower.png",
        "kind": "image",
        "metadata": "",
        "name": "tower.png",
        "smoothed": true,
        "userAdded": false
      },
      {
        "alwaysLoaded": false,
        "file": "assets/Blue laser (16).png",
        "kind": "image",
        "metadata": "",
        "name": "Blue laser (16).png",
        "smoothed": true,
        "userAdded": false,
        "origin": {
          "identifier": "https://resources.gdevelop-app.com/assets/Space Shooter/PNG/Lasers/Blue laser (16).png",
          "name": "gdevelop-asset-store"
        }
      },
      {
        "alwaysLoaded": false,
        "file": "Electric Fence.png",
        "kind": "image",
        "metadata": "",
        "name": "Electric Fence.png",
        "smoothed": true,
        "userAdded": true
      },
      {
        "alwaysLoaded": false,
        "file": "Electric Fence2.png",
        "kind": "image",
        "metadata": "",
        "name": "Electric Fence2.png",
        "smoothed": true,
        "userAdded": false
      },
      {
        "alwaysLoaded": false,
        "file": "assets/Green laser (07).png",
        "kind": "image",
        "metadata": "",
        "name": "Green laser (07).png",
        "smoothed": true,
        "userAdded": false,
        "origin": {
          "identifier": "https://resources.gdevelop-app.com/assets/Space Shooter/PNG/Lasers/Green laser (07).png",
          "name": "gdevelop-asset-store"
        }
      },
      {
        "alwaysLoaded": false,
        "file": "Rectangle 2.png",
        "kind": "image",
        "metadata": "",
        "name": "Rectangle 2.png",
        "smoothed": true,
        "userAdded": true
      },
      {
        "alwaysLoaded": false,
        "file": "Rectangle 1.png",
        "kind": "image",
        "metadata": "",
        "name": "Rectangle 1.png",
        "smoothed": true,
        "userAdded": true
      },
      {
        "alwaysLoaded": false,
        "file": "Rectangle 12.png",
        "kind": "image",
        "metadata": "",
        "name": "Rectangle 12.png",
        "smoothed": true,
        "userAdded": true
      },
      {
        "alwaysLoaded": false,
        "file": "Sem título.png",
        "kind": "image",
        "metadata": "",
        "name": "Sem título.png",
        "smoothed": true,
        "userAdded": false
      },
      {
        "alwaysLoaded": false,
        "file": "fio-fluxo-1.png",
        "kind": "image",
        "metadata": "",
        "name": "fio-fluxo-1.png",
        "smoothed": true,
        "userAdded": false
      },
      {
        "alwaysLoaded": false,
        "file": "fio-fluxo-2.png",
        "kind": "image",
        "metadata": "",
        "name": "fio-fluxo-2.png",
        "smoothed": true,
        "userAdded": false
      },
      {
        "alwaysLoaded": false,
        "file": "fio-fluxo-3.png",
        "kind": "image",
        "metadata": "",
        "name": "fio-fluxo-3.png",
        "smoothed": true,
        "userAdded": false
      },
      {
        "alwaysLoaded": false,
        "file": "fio-fluxo-4.png",
        "kind": "image",
        "metadata": "",
        "name": "fio-fluxo-4.png",
        "smoothed": true,
        "userAdded": false
      },
      {
        "alwaysLoaded": false,
        "file": "fio-fluxo-5.png",
        "kind": "image",
        "metadata": "",
        "name": "fio-fluxo-5.png",
        "smoothed": true,
        "userAdded": false
      },
      {
        "alwaysLoaded": false,
        "file": "fio-fluxo-52.png",
        "kind": "image",
        "metadata": "",
        "name": "fio-fluxo-52.png",
        "smoothed": true,
        "userAdded": false
      },
      {
        "alwaysLoaded": false,
        "file": "Rectangle 13.png",
        "kind": "image",
        "metadata": "",
        "name": "Rectangle 13.png",
        "smoothed": true,
        "userAdded": true
      },
      {
        "alwaysLoaded": false,
        "file": "fio-fluxo-12.png",
        "kind": "image",
        "metadata": "",
        "name": "fio-fluxo-12.png",
        "smoothed": true,
        "userAdded": true
      },
      {
        "alwaysLoaded": false,
        "file": "fio-fluxo-22.png",
        "kind": "image",
        "metadata": "",
        "name": "fio-fluxo-22.png",
        "smoothed": true,
        "userAdded": false
      },
      {
        "alwaysLoaded": false,
        "file": "fio-fluxo-32.png",
        "kind": "image",
        "metadata": "",
        "name": "fio-fluxo-32.png",
        "smoothed": true,
        "userAdded": false
      },
      {
        "alwaysLoaded": false,
        "file": "fio-fluxo-42.png",
        "kind": "image",
        "metadata": "",
        "name": "fio-fluxo-42.png",
        "smoothed": true,
        "userAdded": false
      },
      {
        "alwaysLoaded": false,
        "file": "fio-fluxo-53.png",
        "kind": "image",
        "metadata": "",
        "name": "fio-fluxo-53.png",
        "smoothed": true,
        "userAdded": false
      },
      {
        "alwaysLoaded": false,
        "file": "Rectangle 22.png",
        "kind": "image",
        "metadata": "",
        "name": "Rectangle 22.png",
        "smoothed": true,
        "userAdded": false
      },
      {
        "alwaysLoaded": false,
        "file": "fio2-fluxo-1.png",
        "kind": "image",
        "metadata": "",
        "name": "fio2-fluxo-1.png",
        "smoothed": true,
        "userAdded": false
      },
      {
        "alwaysLoaded": false,
        "file": "fio2-fluxo-2.png",
        "kind": "image",
        "metadata": "",
        "name": "fio2-fluxo-2.png",
        "smoothed": true,
        "userAdded": false
      },
      {
        "alwaysLoaded": false,
        "file": "fio2-fluxo-3.png",
        "kind": "image",
        "metadata": "",
        "name": "fio2-fluxo-3.png",
        "smoothed": true,
        "userAdded": false
      },
      {
        "alwaysLoaded": false,
        "file": "fio2-fluxo-4.png",
        "kind": "image",
        "metadata": "",
        "name": "fio2-fluxo-4.png",
        "smoothed": true,
        "userAdded": false
      },
      {
        "alwaysLoaded": false,
        "file": "fio2-fluxo-5.png",
        "kind": "image",
        "metadata": "",
        "name": "fio2-fluxo-5.png",
        "smoothed": true,
        "userAdded": false
      },
      {
        "alwaysLoaded": false,
        "file": "assets/fios/Rectangle 2.png",
        "kind": "image",
        "metadata": "",
        "name": "assets\\fios\\Rectangle 2.png",
        "smoothed": true,
        "userAdded": true
      },
      {
        "alwaysLoaded": false,
        "file": "assets/fios/animation/fio2-fluxo-1.png",
        "kind": "image",
        "metadata": "",
        "name": "assets\\fios\\animation\\fio2-fluxo-1.png",
        "smoothed": true,
        "userAdded": true
      },
      {
        "alwaysLoaded": false,
        "file": "assets/fios/animation/fio2-fluxo-2.png",
        "kind": "image",
        "metadata": "",
        "name": "assets\\fios\\animation\\fio2-fluxo-2.png",
        "smoothed": true,
        "userAdded": true
      },
      {
        "alwaysLoaded": false,
        "file": "assets/fios/animation/fio2-fluxo-3.png",
        "kind": "image",
        "metadata": "",
        "name": "assets\\fios\\animation\\fio2-fluxo-3.png",
        "smoothed": true,
        "userAdded": true
      },
      {
        "alwaysLoaded": false,
        "file": "assets/fios/animation/fio2-fluxo-4.png",
        "kind": "image",
        "metadata": "",
        "name": "assets\\fios\\animation\\fio2-fluxo-4.png",
        "smoothed": true,
        "userAdded": true
      },
      {
        "alwaysLoaded": false,
        "file": "assets/fios/animation/fio2-fluxo-5.png",
        "kind": "image",
        "metadata": "",
        "name": "assets\\fios\\animation\\fio2-fluxo-5.png",
        "smoothed": true,
        "userAdded": true
      },
      {
        "alwaysLoaded": false,
        "file": "assets/fios/Rectangle 1.png",
        "kind": "image",
        "metadata": "",
        "name": "assets\\fios\\Rectangle 1.png",
        "smoothed": true,
        "userAdded": false
      },
      {
        "alwaysLoaded": false,
        "file": "assets/fios/animation/fio-fluxo-1.png",
        "kind": "image",
        "metadata": "",
        "name": "assets\\fios\\animation\\fio-fluxo-1.png",
        "smoothed": true,
        "userAdded": true
      },
      {
        "alwaysLoaded": false,
        "file": "assets/fios/animation/fio-fluxo-2.png",
        "kind": "image",
        "metadata": "",
        "name": "assets\\fios\\animation\\fio-fluxo-2.png",
        "smoothed": true,
        "userAdded": true
      },
      {
        "alwaysLoaded": false,
        "file": "assets/fios/animation/fio-fluxo-3.png",
        "kind": "image",
        "metadata": "",
        "name": "assets\\fios\\animation\\fio-fluxo-3.png",
        "smoothed": true,
        "userAdded": true
      },
      {
        "alwaysLoaded": false,
        "file": "assets/fios/animation/fio-fluxo-4.png",
        "kind": "image",
        "metadata": "",
        "name": "assets\\fios\\animation\\fio-fluxo-4.png",
        "smoothed": true,
        "userAdded": false
      },
      {
        "alwaysLoaded": false,
        "file": "assets/fios/animation/fio-fluxo-5.png",
        "kind": "image",
        "metadata": "",
        "name": "assets\\fios\\animation\\fio-fluxo-5.png",
        "smoothed": true,
        "userAdded": true
      }
    ],
    "resourceFolders": []
  },
  "objects": [],
  "objectsGroups": [],
  "variables": [
    {
      "name": "copo",
      "value": "0"
    }
  ],
  "layouts": [
    {
      "b": 209,
      "disableInputWhenNotFocused": true,
      "mangledName": "New_32scene",
      "name": "New scene",
      "oglFOV": 90,
      "oglZFar": 500,
      "oglZNear": 1,
      "r": 209,
      "standardSortMethod": true,
      "stopSoundsOnStartup": true,
      "title": "",
      "v": 209,
      "uiSettings": {
        "grid": false,
        "gridB": 255,
        "gridG": 180,
        "gridHeight": 32,
        "gridOffsetX": 0,
        "gridOffsetY": 0,
        "gridR": 158,
        "gridWidth": 32,
        "snap": false,
        "windowMask": false,
        "zoomFactor": 1.024
      },
      "objectsGroups": [
        {
          "name": "Group",
          "objects": [
            {
              "name": "RedDisc"
            }
          ]
        }
      ],
      "variables": [
        {
          "name": "variavel de cena",
          "value": ""
        }
      ],
      "instances": [
        {
          "angle": 0,
          "customSize": true,
          "height": 623,
          "layer": "background image",
          "locked": true,
          "name": "NewObject3",
          "persistentUuid": "97fc956e-59d4-42df-9764-ffab0b68bb77",
          "width": 875,
          "x": -33,
          "y": -3,
          "zOrder": 9,
          "numberProperties": [],
          "stringProperties": [],
          "initialVariables": []
        },
        {
          "angle": 0,
          "customSize": false,
          "height": 0,
          "layer": "",
          "locked": false,
          "name": "RedDisc",
          "persistentUuid": "7dc2bbc4-59fb-4484-8fc2-e7a36585b641",
          "width": 0,
          "x": 64,
          "y": 480,
          "zOrder": 13,
          "numberProperties": [],
          "stringProperties": [],
          "initialVariables": [
            {
              "name": "teste",
              "value": "1"
            }
          ]
        },
        {
          "angle": 0,
          "customSize": false,
          "height": 0,
          "layer": "",
          "locked": false,
          "name": "RedDisc",
          "persistentUuid": "7f44b133-f729-46f3-b7bb-ecdb11b20fd2",
          "width": 0,
          "x": 448,
          "y": 192,
          "zOrder": 14,
          "numberProperties": [],
          "stringProperties": [],
          "initialVariables": []
        },
        {
          "angle": 0,
          "customSize": false,
          "height": 0,
          "layer": "",
          "locked": false,
          "name": "RedDisc",
          "persistentUuid": "8584a202-b12f-4e6c-b3da-1312d6e8f7cb",
          "width": 0,
          "x": 256,
          "y": 192,
          "zOrder": 15,
          "numberProperties": [],
          "stringProperties": [],
          "initialVariables": [
            {
              "name": "teste",
              "value": "3"
            }
          ]
        },
        {
          "angle": 0,
          "customSize": false,
          "height": 0,
          "layer": "",
          "locked": false,
          "name": "RedDisc",
          "persistentUuid": "aa429f56-f22a-4d52-b103-ad20b39dcfa2",
          "width": 0,
          "x": 224,
          "y": 480,
          "zOrder": 13,
          "numberProperties": [],
          "stringProperties": [],
          "initialVariables": []
        },
        {
          "angle": 0,
          "customSize": false,
          "height": 0,
          "layer": "",
          "locked": false,
          "name": "RedDisc",
          "persistentUuid": "8dae7ecf-a931-4ae3-8179-bec989852e9a",
          "width": 0,
          "x": 64,
          "y": 192,
          "zOrder": 16,
          "numberProperties": [],
          "stringProperties": [],
          "initialVariables": []
        },
        {
          "angle": 0,
          "customSize": false,
          "height": 0,
          "layer": "",
          "locked": false,
          "name": "RedDisc",
          "persistentUuid": "9c3ca330-c3c5-4bb4-8b78-be0f336abb36",
          "width": 0,
          "x": 448,
          "y": 480,
          "zOrder": 13,
          "numberProperties": [],
          "stringProperties": [],
          "initialVariables": []
        },
        {
          "angle": 0,
          "customSize": false,
          "height": 0,
          "layer": "",
          "locked": false,
          "name": "RedDisc",
          "persistentUuid": "b0b8018e-a15a-4609-964f-5d6ddfc7c0ea",
          "width": 0,
          "x": 448,
          "y": 320,
          "zOrder": 13,
          "numberProperties": [],
          "stringProperties": [],
          "initialVariables": []
        },
        {
          "angle": 0,
          "customSize": false,
          "height": 0,
          "layer": "",
          "locked": false,
          "name": "RedDisc",
          "persistentUuid": "e4829794-8ecb-4cfb-8a83-67be45fa8452",
          "width": 0,
          "x": 640,
          "y": 448,
          "zOrder": 13,
          "numberProperties": [],
          "stringProperties": [],
          "initialVariables": []
        },
        {
          "angle": -2.25686e-14,
          "customSize": true,
          "height": 8,
          "layer": "",
          "locked": false,
          "name": "FioHor",
          "persistentUuid": "44e755cd-60c1-423d-af6f-f85e4526326f",
          "width": 183,
          "x": 286,
          "y": 205,
          "zOrder": 0,
          "numberProperties": [
            {
              "name": "animation",
              "value": 1
            }
          ],
          "stringProperties": [],
          "initialVariables": []
        },
        {
          "angle": 0,
          "customSize": true,
          "height": 144,
          "layer": "",
          "locked": false,
          "name": "FioVert",
          "persistentUuid": "127a7352-1c99-4e3e-8c43-aced33106bef",
          "width": 7,
          "x": 462,
          "y": 339,
          "zOrder": 0,
          "numberProperties": [
            {
              "name": "animation",
              "value": 1
            }
          ],
          "stringProperties": [],
          "initialVariables": []
        },
        {
          "angle": 0,
          "customSize": true,
          "height": 8,
          "layer": "",
          "locked": false,
          "name": "FioHor",
          "persistentUuid": "3b2b8b9e-525a-49a4-a397-1e94f8603b21",
          "width": 185,
          "x": 276,
          "y": 241,
          "zOrder": 18,
          "numberProperties": [
            {
              "name": "animation",
              "value": 1
            }
          ],
          "stringProperties": [],
          "initialVariables": [
            {
              "name": "left",
              "value": "0"
            }
          ]
        },
        {
          "angle": 0,
          "customSize": true,
          "height": 152,
          "layer": "",
          "locked": false,
          "name": "FioVert",
          "persistentUuid": "536ea432-1f08-4952-8d53-a59f9eeddf49",
          "width": 8,
          "x": 386,
          "y": 336,
          "zOrder": 19,
          "numberProperties": [
            {
              "name": "animation",
              "value": 1
            }
          ],
          "stringProperties": [],
          "initialVariables": [
            {
              "name": "up",
              "value": "0"
            }
          ]
        }
      ],
      "objects": [
        {
          "name": "RedDisc",
          "tags": "",
          "type": "Sprite",
          "updateIfNotVisible": false,
          "variables": [
            {
              "name": "custo",
              "value": "5"
            },
            {
              "name": "fluxo entrada",
              "value": "0"
            },
            {
              "name": "fluxo saída",
              "value": "0"
            }
          ],
          "behaviors": [],
          "animations": [
            {
              "name": "",
              "useMultipleDirections": false,
              "directions": [
                {
                  "looping": true,
                  "timeBetweenFrames": 0.025,
                  "sprites": [
                    {
                      "hasCustomCollisionMask": true,
                      "image": "Red Disc.png",
                      "points": [],
                      "originPoint": {
                        "name": "origine",
                        "x": 0,
                        "y": 0
                      },
                      "centerPoint": {
                        "automatic": true,
                        "name": "centre",
                        "x": 0,
                        "y": 0
                      },
                      "customCollisionMask": [
                        [
                          {
                            "x": 8,
                            "y": 9
                          },
                          {
                            "x": 24,
                            "y": 9
                          },
                          {
                            "x": 25,
                            "y": 25
                          },
                          {
                            "x": 11,
                            "y": 26
                          }
                        ]
                      ]
                    }
                  ]
                }
              ]
            },
            {
              "name": "",
              "useMultipleDirections": false,
              "directions": [
                {
                  "looping": false,
                  "timeBetweenFrames": 0.08,
                  "sprites": [
                    {
                      "hasCustomCollisionMask": true,
                      "image": "assets\\Green Disc.png",
                      "points": [],
                      "originPoint": {
                        "name": "origine",
                        "x": 0,
                        "y": 0
                      },
                      "centerPoint": {
                        "automatic": true,
                        "name": "centre",
                        "x": 0,
                        "y": 0
                      },
                      "customCollisionMask": [
                        [
                          {
                            "x": 8,
                            "y": 9
                          },
                          {
                            "x": 24,
                            "y": 9
                          },
                          {
                            "x": 25,
                            "y": 25
                          },
                          {
                            "x": 11,
                            "y": 26
                          }
                        ]
                      ]
                    }
                  ]
                }
              ]
            }
          ]
        },
        {
          "bottomMargin": 0,
          "height": 32,
          "leftMargin": 0,
          "name": "NewObject3",
          "rightMargin": 0,
          "tags": "",
          "texture": "teste.png",
          "tiled": false,
          "topMargin": 0,
          "type": "PanelSpriteObject::PanelSprite",
          "width": 32,
          "variables": [],
          "behaviors": []
        },
        {
          "name": "GreenLaser07",
          "tags": "",
          "type": "Sprite",
          "updateIfNotVisible": false,
          "variables": [
            {
              "name": "posição x",
              "value": ""
            },
            {
              "name": "posição y",
              "value": ""
            }
          ],
          "behaviors": [],
          "animations": [
            {
              "name": "",
              "useMultipleDirections": false,
              "directions": [
                {
                  "looping": true,
                  "timeBetweenFrames": 0.025,
                  "sprites": [
                    {
                      "hasCustomCollisionMask": false,
                      "image": "Green laser (07).png",
                      "points": [],
                      "originPoint": {
                        "name": "origine",
                        "x": 0,
                        "y": 0
                      },
                      "centerPoint": {
                        "automatic": true,
                        "name": "centre",
                        "x": 0,
                        "y": 0
                      },
                      "customCollisionMask": []
                    }
                  ]
                }
              ]
            }
          ]
        },
        {
          "name": "FioHor",
          "tags": "",
          "type": "Sprite",
          "updateIfNotVisible": false,
          "variables": [
            {
              "name": "left",
              "value": "1"
            }
          ],
          "behaviors": [],
          "animations": [
            {
              "name": "fio",
              "useMultipleDirections": false,
              "directions": [
                {
                  "looping": false,
                  "timeBetweenFrames": 0.1,
                  "sprites": [
                    {
                      "hasCustomCollisionMask": false,
                      "image": "assets\\fios\\Rectangle 1.png",
                      "points": [],
                      "originPoint": {
                        "name": "origine",
                        "x": 0,
                        "y": 0
                      },
                      "centerPoint": {
                        "automatic": true,
                        "name": "centre",
                        "x": 0,
                        "y": 0
                      },
                      "customCollisionMask": []
                    }
                  ]
                }
              ]
            },
            {
              "name": "fio-com-fluxo",
              "useMultipleDirections": false,
              "directions": [
                {
                  "looping": true,
                  "timeBetweenFrames": 0.1,
                  "sprites": [
                    {
                      "hasCustomCollisionMask": false,
                      "image": "assets\\fios\\Rectangle 1.png",
                      "points": [],
                      "originPoint": {
                        "name": "origine",
                        "x": 0,
                        "y": 0
                      },
                      "centerPoint": {
                        "automatic": true,
                        "name": "centre",
                        "x": 0,
                        "y": 0
                      },
                      "customCollisionMask": []
                    },
                    {
                      "hasCustomCollisionMask": false,
                      "image": "assets\\fios\\animation\\fio-fluxo-1.png",
                      "points": [],
                      "originPoint": {
                        "name": "origine",
                        "x": 0,
                        "y": 0
                      },
                      "centerPoint": {
                        "automatic": true,
                        "name": "centre",
                        "x": 0,
                        "y": 0
                      },
                      "customCollisionMask": []
                    },
                    {
                      "hasCustomCollisionMask": false,
                      "image": "assets\\fios\\animation\\fio-fluxo-2.png",
                      "points": [],
                      "originPoint": {
                        "name": "origine",
                        "x": 0,
                        "y": 0
                      },
                      "centerPoint": {
                        "automatic": true,
                        "name": "centre",
                        "x": 0,
                        "y": 0
                      },
                      "customCollisionMask": []
                    },
                    {
                      "hasCustomCollisionMask": false,
                      "image": "assets\\fios\\animation\\fio-fluxo-3.png",
                      "points": [],
                      "originPoint": {
                        "name": "origine",
                        "x": 0,
                        "y": 0
                      },
                      "centerPoint": {
                        "automatic": true,
                        "name": "centre",
                        "x": 0,
                        "y": 0
                      },
                      "customCollisionMask": []
                    },
                    {
                      "hasCustomCollisionMask": false,
                      "image": "assets\\fios\\animation\\fio-fluxo-4.png",
                      "points": [],
                      "originPoint": {
                        "name": "origine",
                        "x": 0,
                        "y": 0
                      },
                      "centerPoint": {
                        "automatic": true,
                        "name": "centre",
                        "x": 0,
                        "y": 0
                      },
                      "customCollisionMask": []
                    },
                    {
                      "hasCustomCollisionMask": false,
                      "image": "assets\\fios\\animation\\fio-fluxo-5.png",
                      "points": [],
                      "originPoint": {
                        "name": "origine",
                        "x": 0,
                        "y": 0
                      },
                      "centerPoint": {
                        "automatic": true,
                        "name": "centre",
                        "x": 0,
                        "y": 0
                      },
                      "customCollisionMask": []
                    }
                  ]
                }
              ]
            }
          ]
        },
        {
          "name": "FioVert",
          "tags": "",
          "type": "Sprite",
          "updateIfNotVisible": false,
          "variables": [
            {
              "name": "up",
              "value": "1"
            }
          ],
          "behaviors": [],
          "animations": [
            {
              "name": "fio2",
              "useMultipleDirections": false,
              "directions": [
                {
                  "looping": false,
                  "timeBetweenFrames": 0.08,
                  "sprites": [
                    {
                      "hasCustomCollisionMask": false,
                      "image": "assets\\fios\\Rectangle 2.png",
                      "points": [],
                      "originPoint": {
                        "name": "origine",
                        "x": 0,
                        "y": 0
                      },
                      "centerPoint": {
                        "automatic": true,
                        "name": "centre",
                        "x": 0,
                        "y": 0
                      },
                      "customCollisionMask": []
                    }
                  ]
                }
              ]
            },
            {
              "name": "fio2-com-fluxo",
              "useMultipleDirections": false,
              "directions": [
                {
                  "looping": true,
                  "timeBetweenFrames": 0.1,
                  "sprites": [
                    {
                      "hasCustomCollisionMask": false,
                      "image": "assets\\fios\\Rectangle 2.png",
                      "points": [],
                      "originPoint": {
                        "name": "origine",
                        "x": 0,
                        "y": 0
                      },
                      "centerPoint": {
                        "automatic": true,
                        "name": "centre",
                        "x": 0,
                        "y": 0
                      },
                      "customCollisionMask": []
                    },
                    {
                      "hasCustomCollisionMask": false,
                      "image": "assets\\fios\\animation\\fio2-fluxo-1.png",
                      "points": [],
                      "originPoint": {
                        "name": "origine",
                        "x": 0,
                        "y": 0
                      },
                      "centerPoint": {
                        "automatic": true,
                        "name": "centre",
                        "x": 0,
                        "y": 0
                      },
                      "customCollisionMask": []
                    },
                    {
                      "hasCustomCollisionMask": false,
                      "image": "assets\\fios\\animation\\fio2-fluxo-2.png",
                      "points": [],
                      "originPoint": {
                        "name": "origine",
                        "x": 0,
                        "y": 0
                      },
                      "centerPoint": {
                        "automatic": true,
                        "name": "centre",
                        "x": 0,
                        "y": 0
                      },
                      "customCollisionMask": []
                    },
                    {
                      "hasCustomCollisionMask": false,
                      "image": "assets\\fios\\animation\\fio2-fluxo-3.png",
                      "points": [],
                      "originPoint": {
                        "name": "origine",
                        "x": 0,
                        "y": 0
                      },
                      "centerPoint": {
                        "automatic": true,
                        "name": "centre",
                        "x": 0,
                        "y": 0
                      },
                      "customCollisionMask": []
                    },
                    {
                      "hasCustomCollisionMask": false,
                      "image": "assets\\fios\\animation\\fio2-fluxo-4.png",
                      "points": [],
                      "originPoint": {
                        "name": "origine",
                        "x": 0,
                        "y": 0
                      },
                      "centerPoint": {
                        "automatic": true,
                        "name": "centre",
                        "x": 0,
                        "y": 0
                      },
                      "customCollisionMask": []
                    },
                    {
                      "hasCustomCollisionMask": false,
                      "image": "assets\\fios\\animation\\fio2-fluxo-5.png",
                      "points": [],
                      "originPoint": {
                        "name": "origine",
                        "x": 0,
                        "y": 0
                      },
                      "centerPoint": {
                        "automatic": true,
                        "name": "centre",
                        "x": 0,
                        "y": 0
                      },
                      "customCollisionMask": []
                    }
                  ]
                }
              ]
            }
          ]
        }
      ],
      "events": [
        {
          "colorB": 228,
          "colorG": 176,
          "colorR": 74,
          "creationTime": 0,
          "disabled": false,
          "folded": false,
          "name": "changing object instance variables",
          "source": "",
          "type": "BuiltinCommonInstructions::Group",
          "events": [
            {
              "disabled": false,
              "folded": false,
              "type": "BuiltinCommonInstructions::Standard",
              "conditions": [
                {
                  "type": {
                    "inverted": false,
                    "value": "VarObjet"
                  },
                  "parameters": [
                    "RedDisc",
                    "teste",
                    "=",
                    "0"
                  ],
                  "subInstructions": []
                }
              ],
              "actions": [],
              "events": [
                {
                  "disabled": false,
                  "folded": false,
                  "type": "BuiltinCommonInstructions::Standard",
                  "conditions": [
                    {
                      "type": {
                        "inverted": false,
                        "value": "SourisBouton"
                      },
                      "parameters": [
                        "",
                        "Left"
                      ],
                      "subInstructions": []
                    },
                    {
                      "type": {
                        "inverted": false,
                        "value": "SourisSurObjet"
                      },
                      "parameters": [
                        "RedDisc",
                        "",
                        "yes",
                        ""
                      ],
                      "subInstructions": []
                    }
                  ],
                  "actions": [
                    {
                      "type": {
                        "inverted": false,
                        "value": "ModVarObjet"
                      },
                      "parameters": [
                        "RedDisc",
                        "teste",
                        "=",
                        "1"
                      ],
                      "subInstructions": []
                    },
                    {
                      "type": {
                        "inverted": false,
                        "value": "ChangeAnimation"
                      },
                      "parameters": [
                        "RedDisc",
                        "=",
                        "1"
                      ],
                      "subInstructions": []
                    }
                  ],
                  "events": []
                }
              ]
            },
            {
              "disabled": false,
              "folded": false,
              "type": "BuiltinCommonInstructions::Standard",
              "conditions": [
                {
                  "type": {
                    "inverted": false,
                    "value": "VarObjet"
                  },
                  "parameters": [
                    "RedDisc",
                    "teste",
                    "=",
                    "1"
                  ],
                  "subInstructions": []
                }
              ],
              "actions": [],
              "events": [
                {
                  "disabled": false,
                  "folded": false,
                  "type": "BuiltinCommonInstructions::Standard",
                  "conditions": [
                    {
                      "type": {
                        "inverted": false,
                        "value": "SourisBouton"
                      },
                      "parameters": [
                        "",
                        "Left"
                      ],
                      "subInstructions": []
                    },
                    {
                      "type": {
                        "inverted": true,
                        "value": "SourisSurObjet"
                      },
                      "parameters": [
                        "RedDisc",
                        "",
                        "",
                        ""
                      ],
                      "subInstructions": []
                    }
                  ],
                  "actions": [
                    {
                      "type": {
                        "inverted": false,
                        "value": "ModVarObjet"
                      },
                      "parameters": [
                        "RedDisc",
                        "teste",
                        "=",
                        "0"
                      ],
                      "subInstructions": []
                    },
                    {
                      "type": {
                        "inverted": false,
                        "value": "ChangeAnimation"
                      },
                      "parameters": [
                        "RedDisc",
                        "=",
                        "0"
                      ],
                      "subInstructions": []
                    }
                  ],
                  "events": []
                },
                {
                  "disabled": false,
                  "folded": false,
                  "type": "BuiltinCommonInstructions::Standard",
                  "conditions": [],
                  "actions": [],
                  "events": []
                }
              ]
            }
          ],
          "parameters": []
        },
        {
          "colorB": 228,
          "colorG": 176,
          "colorR": 74,
          "creationTime": 0,
          "disabled": false,
          "folded": false,
          "name": "Colisão",
          "source": "",
          "type": "BuiltinCommonInstructions::Group",
          "events": [
            {
              "disabled": false,
              "folded": false,
              "type": "BuiltinCommonInstructions::Standard",
              "conditions": [
                {
                  "type": {
                    "inverted": false,
                    "value": "CollisionNP"
                  },
                  "parameters": [
                    "FioHor",
                    "RedDisc",
                    "",
                    "",
                    "no"
                  ],
                  "subInstructions": []
                }
              ],
              "actions": [
                {
                  "type": {
                    "inverted": false,
                    "value": "ChangeAnimation"
                  },
                  "parameters": [
                    "RedDisc",
                    "=",
                    "1"
                  ],
                  "subInstructions": []
                }
              ],
              "events": []
            },
            {
              "disabled": false,
              "folded": false,
              "type": "BuiltinCommonInstructions::Standard",
              "conditions": [
                {
                  "type": {
                    "inverted": false,
                    "value": "CollisionNP"
                  },
                  "parameters": [
                    "FioVert",
                    "RedDisc",
                    "",
                    "",
                    "no"
                  ],
                  "subInstructions": []
                }
              ],
              "actions": [
                {
                  "type": {
                    "inverted": false,
                    "value": "ChangeAnimation"
                  },
                  "parameters": [
                    "RedDisc",
                    "=",
                    "1"
                  ],
                  "subInstructions": []
                }
              ],
              "events": []
            },
            {
              "disabled": false,
              "folded": false,
              "type": "BuiltinCommonInstructions::Standard",
              "conditions": [
                {
                  "type": {
                    "inverted": false,
                    "value": "VarObjet"
                  },
                  "parameters": [
                    "FioHor",
                    "left",
                    "=",
                    "0"
                  ],
                  "subInstructions": []
                }
              ],
              "actions": [
                {
                  "type": {
                    "inverted": false,
                    "value": "FlipX"
                  },
                  "parameters": [
                    "FioHor",
                    "yes"
                  ],
                  "subInstructions": []
                }
              ],
              "events": []
            },
            {
              "disabled": false,
              "folded": false,
              "type": "BuiltinCommonInstructions::Standard",
              "conditions": [
                {
                  "type": {
                    "inverted": false,
                    "value": "VarObjet"
                  },
                  "parameters": [
                    "FioVert",
                    "up",
                    "=",
                    "0"
                  ],
                  "subInstructions": []
                }
              ],
              "actions": [
                {
                  "type": {
                    "inverted": false,
                    "value": "FlipY"
                  },
                  "parameters": [
                    "FioVert",
                    "yes"
                  ],
                  "subInstructions": []
                }
              ],
              "events": []
            }
          ],
          "parameters": []
        }
      ],
      "layers": [
        {
          "ambientLightColorB": 1702453632,
          "ambientLightColorG": 1333224832,
          "ambientLightColorR": 167785328,
          "followBaseLayerCamera": false,
          "isLightingLayer": false,
          "name": "background image",
          "visibility": true,
          "cameras": [],
          "effects": []
        },
        {
          "ambientLightColorB": 36,
          "ambientLightColorG": 7163208,
          "ambientLightColorR": 32,
          "followBaseLayerCamera": false,
          "isLightingLayer": false,
          "name": "",
          "visibility": true,
          "cameras": [
            {
              "defaultSize": true,
              "defaultViewport": true,
              "height": 0,
              "viewportBottom": 1,
              "viewportLeft": 0,
              "viewportRight": 1,
              "viewportTop": 0,
              "width": 0
            }
          ],
          "effects": []
        }
      ],
      "behaviorsSharedData": []
    }
  ],
  "externalEvents": [],
  "eventsFunctionsExtensions": [],
  "externalLayouts": [],
  "externalSourceFiles": []
}